openlca2bw/IPC_Extractor.py
openlca2bw/Json_Extractor.py
openlca2bw/__init__.py
openlca2bw/_version.py
openlca2bw/allocation.py
openlca2bw/bw_write.py
openlca2bw/extract.py
openlca2bw/main.py
openlca2bw/utils.py
openlca2bw-1.0.0.dist-info/LICENSE.md
openlca2bw-1.0.0.dist-info/METADATA
openlca2bw-1.0.0.dist-info/WHEEL
openlca2bw-1.0.0.dist-info/top_level.txt
openlca2bw-1.0.0.dist-info/RECORD
