Metadata-Version: 2.1
Name: openlca2bw
Version: 1.0.0
Summary: A Python package to extract and write an LCA database from OpenLCA to Brightway2
Home-page: https://github.com/cyrillefrancois/openlca2bw
Author: Cyrille François
Author-email: cyrille.francois.pro@gmail.com
License: BSD-3
Keywords: open life-cycle analysis,openLCA,brightway
Classifier: Development Status :: 4 - Beta
Classifier: Intended Audience :: Science/Research
Classifier: License :: OSI Approved :: BSD License
Classifier: Programming Language :: Python :: 3.8
License-File: LICENSE.md
Requires-Dist: olca-ipc
Requires-Dist: brightway2
Requires-Dist: stats-arrays
Requires-Dist: urllib3
Requires-Dist: pyprind
Requires-Dist: pandas
